{"path":"%D0%A2%D1%80%D1%91%D1%85%D1%80%D1%91%D0%B1%D0%B5%D1%80%D0%BD%D0%B8%D0%BA%20%D0%BF%D1%80%D0%BE%D0%B4%D1%8B%D1%80%D1%8F%D0%B2%D0%BB%D0%B5%D0%BD%D0%BD%D1%8B%D0%B9%20-%20Tripleurospermum%20inodorum","deepCounters":{"total":20,"images":20,"files":20},"counters":{"total":20,"images":20,"files":20},"thumb":{"path":"thumbs\/DSC09713.webp","width":512,"height":410},"thumbCaption":"<h3>Трёхрёберник продырявленный - Tripleurospermum inodorum<\/h3>","album":{"description":"Herbarium.INFO Herbarium Photo Collection: Ferns, Conifers, Cycads, Flowers, Trees, Mosses, Grasses, Pests and Diseases.<br\/>\n<br\/><i><b>3111<\/b> species in <b>219<\/b> families photographed.<br\/>\n<br\/><b>35552<\/b> images total.<\/i><br\/><br\/>\nTry also other sites: <br\/>\n    <a href=\"https:\/\/herbarium.info\">Herbarium.INFO<\/a>&nbsp;\u2022&nbsp;\n    <a href=\"https:\/\/plantarium.info\">Plantarium.INFO<\/a>&nbsp;\u2022&nbsp;\n    <a href=\"https:\/\/fungarium.info\">Fungarium.INFO<\/a>&nbsp;\u2022&nbsp;\n    <a href=\"https:\/\/lichenarium.info\">Lichenarium.INFO<\/a>&nbsp;\u2022&nbsp;\n    <a href=\"https:\/\/algaerium.info\">Algaerium.INFO<\/a>","title":"Herbarium.INFO Herbs: Dicotyledones & Monocotyledones"},"objects":[{"path":"DSC02180.webp","image":{"path":"slides\/DSC02180.webp","width":1024,"height":768},"imageCaption":"<h5>DSC02180<\/h5>","thumb":{"path":"thumbs\/DSC02180.webp","width":512,"height":410},"fileSize":1052629,"photodata":"<b>Original Date<\/b> <i>7\/19\/12, 2:09 PM<\/i> &middot; <b>Make<\/b> <i>SONY<\/i> &middot; <b>Camera<\/b> <i>DSC-T30<\/i> &middot; <b>Focal Length (35mm)<\/b> <i>38mm<\/i> &middot; <b>Metering Mode<\/b> <i>Multi-segment<\/i> &middot; <b>ISO Equivalent<\/b> <i>125<\/i> &middot; <b>Exposure Time<\/b> <i>1\/640s<\/i> &middot; <b>Aperture<\/b> <i>ƒ\/5.6<\/i> &middot; <b>Exposure bias<\/b> <i>0 EV<\/i> &middot; <b>Exposure Program<\/b> <i>Program normal<\/i> &middot; <b>White balance<\/b> <i>Auto white balance<\/i> &middot; <b>Flash<\/b> <i>Flash did not fire<\/i> &middot; <b>Resolution<\/b> <i>2048 x 1536<\/i>","name":"DSC02180.webp","comment":"                               ","dates":{"dateTaken":1342696167,"fileModified":1394909094},"fileDate":"2014-03-15T20:44:54.0Z","category":"image","camera":{"aperture":5.6,"exposureTime":"1\/640s","originalDate":"2012-07-19T14:09:27.0Z","cameraModel":"DSC-T30","focalLength35mm":"38mm","resolution":"2048 x 1536","cameraMake":"SONY","isoEquivalent":125,"flash":"Flash did not fire","focalLength":"6mm"}},{"path":"DSC02181.webp","image":{"path":"slides\/DSC02181.webp","width":1024,"height":768},"imageCaption":"<h5>DSC02181<\/h5>","thumb":{"path":"thumbs\/DSC02181.webp","width":512,"height":410},"fileSize":1042668,"photodata":"<b>Original Date<\/b> <i>7\/19\/12, 2:09 PM<\/i> &middot; <b>Make<\/b> <i>SONY<\/i> &middot; <b>Camera<\/b> <i>DSC-T30<\/i> &middot; <b>Focal Length (35mm)<\/b> <i>38mm<\/i> &middot; <b>Metering Mode<\/b> <i>Multi-segment<\/i> &middot; <b>ISO Equivalent<\/b> <i>125<\/i> &middot; <b>Exposure Time<\/b> <i>1\/800s<\/i> &middot; <b>Aperture<\/b> <i>ƒ\/5.6<\/i> &middot; <b>Exposure bias<\/b> <i>0 EV<\/i> &middot; <b>Exposure Program<\/b> <i>Program normal<\/i> &middot; <b>White balance<\/b> <i>Auto white balance<\/i> &middot; <b>Flash<\/b> <i>Flash did not fire<\/i> &middot; <b>Resolution<\/b> <i>2048 x 1536<\/i>","name":"DSC02181.webp","comment":"                               ","dates":{"dateTaken":1342696170,"fileModified":1394909094},"fileDate":"2014-03-15T20:44:54.0Z","category":"image","camera":{"aperture":5.6,"exposureTime":"1\/800s","originalDate":"2012-07-19T14:09:30.0Z","cameraModel":"DSC-T30","focalLength35mm":"38mm","resolution":"2048 x 1536","cameraMake":"SONY","isoEquivalent":125,"flash":"Flash did not fire","focalLength":"6mm"}},{"path":"DSC03877.webp","image":{"path":"slides\/DSC03877.webp","width":768,"height":1024},"imageCaption":"<h5>DSC03877<\/h5>","thumb":{"path":"thumbs\/DSC03877.webp","width":512,"height":410},"fileSize":574259,"photodata":"<b>Original Date<\/b> <i>7\/8\/10, 12:35 AM<\/i>","name":"DSC03877.webp","dates":{"dateTaken":1278538536,"fileModified":1394909094},"fileDate":"2014-03-15T20:44:54.0Z","category":"image","camera":{"originalDate":"2010-07-08T00:35:36.0Z"}},{"path":"DSC03958.webp","image":{"path":"slides\/DSC03958.webp","width":768,"height":1024},"imageCaption":"<h5>DSC03958<\/h5>","thumb":{"path":"thumbs\/DSC03958.webp","width":512,"height":410},"fileSize":644541,"photodata":"<b>Original Date<\/b> <i>7\/9\/10, 4:11 PM<\/i>","name":"DSC03958.webp","dates":{"dateTaken":1278681100,"fileModified":1394909094},"fileDate":"2014-03-15T20:44:54.0Z","category":"image","camera":{"originalDate":"2010-07-09T16:11:40.0Z"}},{"path":"DSC04239.webp","image":{"path":"slides\/DSC04239.webp","width":1024,"height":768},"imageCaption":"<h5>DSC04239<\/h5>","thumb":{"path":"thumbs\/DSC04239.webp","width":512,"height":410},"fileSize":1141212,"photodata":"<b>Original Date<\/b> <i>7\/14\/10, 10:03 AM<\/i> &middot; <b>Make<\/b> <i>SONY<\/i> &middot; <b>Camera<\/b> <i>DSC-T30<\/i> &middot; <b>Focal Length (35mm)<\/b> <i>38mm<\/i> &middot; <b>Metering Mode<\/b> <i>Multi-segment<\/i> &middot; <b>ISO Equivalent<\/b> <i>125<\/i> &middot; <b>Exposure Time<\/b> <i>1\/320s<\/i> &middot; <b>Aperture<\/b> <i>ƒ\/5.6<\/i> &middot; <b>Exposure bias<\/b> <i>0 EV<\/i> &middot; <b>Exposure Program<\/b> <i>Program normal<\/i> &middot; <b>White balance<\/b> <i>Auto white balance<\/i> &middot; <b>Flash<\/b> <i>Flash did not fire<\/i> &middot; <b>Resolution<\/b> <i>2048 x 1536<\/i>","name":"DSC04239.webp","comment":"                               ","dates":{"dateTaken":1279091001,"fileModified":1394909094},"fileDate":"2014-03-15T20:44:54.0Z","category":"image","camera":{"aperture":5.6,"exposureTime":"1\/320s","originalDate":"2010-07-14T10:03:21.0Z","cameraModel":"DSC-T30","focalLength35mm":"38mm","resolution":"2048 x 1536","cameraMake":"SONY","isoEquivalent":125,"flash":"Flash did not fire","focalLength":"6mm"}},{"path":"DSC07609.webp","image":{"path":"slides\/DSC07609.webp","width":1536,"height":1152},"imageCaption":"<h5>DSC07609<\/h5>","thumb":{"path":"thumbs\/DSC07609.webp","width":512,"height":410},"fileSize":645855,"photodata":"<b>Original Date<\/b> <i>6\/18\/13, 7:43 PM<\/i> &middot; <b>Make<\/b> <i>SONY<\/i> &middot; <b>Camera<\/b> <i>DSC-T30<\/i> &middot; <b>Focal Length (35mm)<\/b> <i>38mm<\/i> &middot; <b>Metering Mode<\/b> <i>Multi-segment<\/i> &middot; <b>ISO Equivalent<\/b> <i>125<\/i> &middot; <b>Exposure Time<\/b> <i>1\/200s<\/i> &middot; <b>Aperture<\/b> <i>ƒ\/3.5<\/i> &middot; <b>Exposure bias<\/b> <i>0 EV<\/i> &middot; <b>Exposure Program<\/b> <i>Program normal<\/i> &middot; <b>White balance<\/b> <i>Auto white balance<\/i> &middot; <b>Flash<\/b> <i>Flash did not fire<\/i> &middot; <b>Resolution<\/b> <i>3072 x 2304<\/i>","name":"DSC07609.webp","comment":"                               ","dates":{"dateTaken":1371573839,"fileModified":1394909096},"fileDate":"2014-03-15T20:44:56.0Z","category":"image","camera":{"aperture":3.5,"exposureTime":"1\/200s","originalDate":"2013-06-18T19:43:59.0Z","cameraModel":"DSC-T30","focalLength35mm":"38mm","resolution":"3072 x 2304","cameraMake":"SONY","isoEquivalent":125,"flash":"Flash did not fire","focalLength":"6mm"}},{"path":"DSC07610.webp","image":{"path":"slides\/DSC07610.webp","width":1152,"height":1536},"imageCaption":"<h5>DSC07610<\/h5>","thumb":{"path":"thumbs\/DSC07610.webp","width":512,"height":410},"fileSize":927449,"photodata":"<b>Original Date<\/b> <i>6\/18\/13, 7:44 PM<\/i> &middot; <b>Make<\/b> <i>SONY<\/i> &middot; <b>Camera<\/b> <i>DSC-T30<\/i> &middot; <b>Focal Length (35mm)<\/b> <i>38mm<\/i> &middot; <b>Metering Mode<\/b> <i>Multi-segment<\/i> &middot; <b>ISO Equivalent<\/b> <i>125<\/i> &middot; <b>Exposure Time<\/b> <i>1\/50s<\/i> &middot; <b>Aperture<\/b> <i>ƒ\/3.5<\/i> &middot; <b>Exposure bias<\/b> <i>0 EV<\/i> &middot; <b>Exposure Program<\/b> <i>Program normal<\/i> &middot; <b>White balance<\/b> <i>Auto white balance<\/i> &middot; <b>Flash<\/b> <i>Flash did not fire<\/i> &middot; <b>Resolution<\/b> <i>2304 x 3072<\/i>","name":"DSC07610.webp","comment":"                               ","dates":{"dateTaken":1371573848,"fileModified":1394909096},"fileDate":"2014-03-15T20:44:56.0Z","category":"image","camera":{"aperture":3.5,"exposureTime":"1\/50s","originalDate":"2013-06-18T19:44:08.0Z","cameraModel":"DSC-T30","focalLength35mm":"38mm","resolution":"2304 x 3072","cameraMake":"SONY","isoEquivalent":125,"flash":"Flash did not fire","focalLength":"6mm"}},{"path":"DSC07611.webp","image":{"path":"slides\/DSC07611.webp","width":1152,"height":1536},"imageCaption":"<h5>DSC07611<\/h5>","thumb":{"path":"thumbs\/DSC07611.webp","width":512,"height":410},"fileSize":1106686,"photodata":"<b>Original Date<\/b> <i>6\/18\/13, 7:44 PM<\/i> &middot; <b>Make<\/b> <i>SONY<\/i> &middot; <b>Camera<\/b> <i>DSC-T30<\/i> &middot; <b>Focal Length (35mm)<\/b> <i>38mm<\/i> &middot; <b>Metering Mode<\/b> <i>Multi-segment<\/i> &middot; <b>ISO Equivalent<\/b> <i>125<\/i> &middot; <b>Exposure Time<\/b> <i>1\/40s<\/i> &middot; <b>Aperture<\/b> <i>ƒ\/3.5<\/i> &middot; <b>Exposure bias<\/b> <i>0 EV<\/i> &middot; <b>Exposure Program<\/b> <i>Program normal<\/i> &middot; <b>White balance<\/b> <i>Auto white balance<\/i> &middot; <b>Flash<\/b> <i>Flash did not fire<\/i> &middot; <b>Resolution<\/b> <i>2304 x 3072<\/i>","name":"DSC07611.webp","comment":"                               ","dates":{"dateTaken":1371573856,"fileModified":1394909096},"fileDate":"2014-03-15T20:44:56.0Z","category":"image","camera":{"aperture":3.5,"exposureTime":"1\/40s","originalDate":"2013-06-18T19:44:16.0Z","cameraModel":"DSC-T30","focalLength35mm":"38mm","resolution":"2304 x 3072","cameraMake":"SONY","isoEquivalent":125,"flash":"Flash did not fire","focalLength":"6mm"}},{"path":"DSC07612.webp","image":{"path":"slides\/DSC07612.webp","width":1536,"height":1152},"imageCaption":"<h5>DSC07612<\/h5>","thumb":{"path":"thumbs\/DSC07612.webp","width":512,"height":410},"fileSize":1403227,"photodata":"<b>Original Date<\/b> <i>6\/18\/13, 7:44 PM<\/i> &middot; <b>Make<\/b> <i>SONY<\/i> &middot; <b>Camera<\/b> <i>DSC-T30<\/i> &middot; <b>Focal Length (35mm)<\/b> <i>38mm<\/i> &middot; <b>Metering Mode<\/b> <i>Multi-segment<\/i> &middot; <b>ISO Equivalent<\/b> <i>125<\/i> &middot; <b>Exposure Time<\/b> <i>1\/60s<\/i> &middot; <b>Aperture<\/b> <i>ƒ\/3.5<\/i> &middot; <b>Exposure bias<\/b> <i>0 EV<\/i> &middot; <b>Exposure Program<\/b> <i>Program normal<\/i> &middot; <b>White balance<\/b> <i>Auto white balance<\/i> &middot; <b>Flash<\/b> <i>Flash did not fire<\/i> &middot; <b>Resolution<\/b> <i>3072 x 2304<\/i>","name":"DSC07612.webp","comment":"                               ","dates":{"dateTaken":1371573867,"fileModified":1394909096},"fileDate":"2014-03-15T20:44:56.0Z","category":"image","camera":{"aperture":3.5,"exposureTime":"1\/60s","originalDate":"2013-06-18T19:44:27.0Z","cameraModel":"DSC-T30","focalLength35mm":"38mm","resolution":"3072 x 2304","cameraMake":"SONY","isoEquivalent":125,"flash":"Flash did not fire","focalLength":"6mm"}},{"path":"DSC07613.webp","image":{"path":"slides\/DSC07613.webp","width":1152,"height":1536},"imageCaption":"<h5>DSC07613<\/h5>","thumb":{"path":"thumbs\/DSC07613.webp","width":512,"height":410},"fileSize":976331,"photodata":"<b>Original Date<\/b> <i>6\/18\/13, 7:44 PM<\/i> &middot; <b>Make<\/b> <i>SONY<\/i> &middot; <b>Camera<\/b> <i>DSC-T30<\/i> &middot; <b>Focal Length (35mm)<\/b> <i>38mm<\/i> &middot; <b>Metering Mode<\/b> <i>Multi-segment<\/i> &middot; <b>ISO Equivalent<\/b> <i>160<\/i> &middot; <b>Exposure Time<\/b> <i>1\/40s<\/i> &middot; <b>Aperture<\/b> <i>ƒ\/3.5<\/i> &middot; <b>Exposure bias<\/b> <i>0 EV<\/i> &middot; <b>Exposure Program<\/b> <i>Program normal<\/i> &middot; <b>White balance<\/b> <i>Auto white balance<\/i> &middot; <b>Flash<\/b> <i>Flash did not fire<\/i> &middot; <b>Resolution<\/b> <i>2304 x 3072<\/i>","name":"DSC07613.webp","comment":"                               ","dates":{"dateTaken":1371573883,"fileModified":1394909096},"fileDate":"2014-03-15T20:44:56.0Z","category":"image","camera":{"aperture":3.5,"exposureTime":"1\/40s","originalDate":"2013-06-18T19:44:43.0Z","cameraModel":"DSC-T30","focalLength35mm":"38mm","resolution":"2304 x 3072","cameraMake":"SONY","isoEquivalent":160,"flash":"Flash did not fire","focalLength":"6mm"}},{"path":"DSC07614.webp","image":{"path":"slides\/DSC07614.webp","width":1152,"height":1536},"imageCaption":"<h5>DSC07614<\/h5>","thumb":{"path":"thumbs\/DSC07614.webp","width":512,"height":410},"fileSize":1066304,"photodata":"<b>Original Date<\/b> <i>6\/18\/13, 7:44 PM<\/i> &middot; <b>Make<\/b> <i>SONY<\/i> &middot; <b>Camera<\/b> <i>DSC-T30<\/i> &middot; <b>Focal Length (35mm)<\/b> <i>38mm<\/i> &middot; <b>Metering Mode<\/b> <i>Multi-segment<\/i> &middot; <b>ISO Equivalent<\/b> <i>125<\/i> &middot; <b>Exposure Time<\/b> <i>1\/50s<\/i> &middot; <b>Aperture<\/b> <i>ƒ\/3.5<\/i> &middot; <b>Exposure bias<\/b> <i>0 EV<\/i> &middot; <b>Exposure Program<\/b> <i>Program normal<\/i> &middot; <b>White balance<\/b> <i>Auto white balance<\/i> &middot; <b>Flash<\/b> <i>Flash did not fire<\/i> &middot; <b>Resolution<\/b> <i>2304 x 3072<\/i>","name":"DSC07614.webp","comment":"                               ","dates":{"dateTaken":1371573894,"fileModified":1394909096},"fileDate":"2014-03-15T20:44:56.0Z","category":"image","camera":{"aperture":3.5,"exposureTime":"1\/50s","originalDate":"2013-06-18T19:44:54.0Z","cameraModel":"DSC-T30","focalLength35mm":"38mm","resolution":"2304 x 3072","cameraMake":"SONY","isoEquivalent":125,"flash":"Flash did not fire","focalLength":"6mm"}},{"path":"DSC08028.webp","image":{"path":"slides\/DSC08028.webp","width":1536,"height":1152},"imageCaption":"<h5>DSC08028<\/h5>","thumb":{"path":"thumbs\/DSC08028.webp","width":512,"height":410},"fileSize":1202571,"photodata":"<b>Original Date<\/b> <i>6\/24\/13, 7:52 PM<\/i> &middot; <b>Make<\/b> <i>SONY<\/i> &middot; <b>Camera<\/b> <i>DSC-T30<\/i> &middot; <b>Focal Length (35mm)<\/b> <i>38mm<\/i> &middot; <b>Metering Mode<\/b> <i>Multi-segment<\/i> &middot; <b>ISO Equivalent<\/b> <i>125<\/i> &middot; <b>Exposure Time<\/b> <i>1\/160s<\/i> &middot; <b>Aperture<\/b> <i>ƒ\/3.5<\/i> &middot; <b>Exposure bias<\/b> <i>0 EV<\/i> &middot; <b>Exposure Program<\/b> <i>Program normal<\/i> &middot; <b>White balance<\/b> <i>Auto white balance<\/i> &middot; <b>Flash<\/b> <i>Flash did not fire<\/i> &middot; <b>Resolution<\/b> <i>3072 x 2304<\/i>","name":"DSC08028.webp","comment":"                               ","dates":{"dateTaken":1372092723,"fileModified":1394909096},"fileDate":"2014-03-15T20:44:56.0Z","category":"image","camera":{"aperture":3.5,"exposureTime":"1\/160s","originalDate":"2013-06-24T19:52:03.0Z","cameraModel":"DSC-T30","focalLength35mm":"38mm","resolution":"3072 x 2304","cameraMake":"SONY","isoEquivalent":125,"flash":"Flash did not fire","focalLength":"6mm"}},{"path":"DSC08029.webp","image":{"path":"slides\/DSC08029.webp","width":1536,"height":1152},"imageCaption":"<h5>DSC08029<\/h5>","thumb":{"path":"thumbs\/DSC08029.webp","width":512,"height":410},"fileSize":1348295,"photodata":"<b>Original Date<\/b> <i>6\/24\/13, 7:52 PM<\/i> &middot; <b>Make<\/b> <i>SONY<\/i> &middot; <b>Camera<\/b> <i>DSC-T30<\/i> &middot; <b>Focal Length (35mm)<\/b> <i>38mm<\/i> &middot; <b>Metering Mode<\/b> <i>Multi-segment<\/i> &middot; <b>ISO Equivalent<\/b> <i>160<\/i> &middot; <b>Exposure Time<\/b> <i>1\/40s<\/i> &middot; <b>Aperture<\/b> <i>ƒ\/3.5<\/i> &middot; <b>Exposure bias<\/b> <i>0 EV<\/i> &middot; <b>Exposure Program<\/b> <i>Program normal<\/i> &middot; <b>White balance<\/b> <i>Auto white balance<\/i> &middot; <b>Flash<\/b> <i>Flash did not fire<\/i> &middot; <b>Resolution<\/b> <i>3072 x 2304<\/i>","name":"DSC08029.webp","comment":"                               ","dates":{"dateTaken":1372092758,"fileModified":1394909096},"fileDate":"2014-03-15T20:44:56.0Z","category":"image","camera":{"aperture":3.5,"exposureTime":"1\/40s","originalDate":"2013-06-24T19:52:38.0Z","cameraModel":"DSC-T30","focalLength35mm":"38mm","resolution":"3072 x 2304","cameraMake":"SONY","isoEquivalent":160,"flash":"Flash did not fire","focalLength":"6mm"}},{"path":"DSC08030.webp","image":{"path":"slides\/DSC08030.webp","width":1536,"height":1152},"imageCaption":"<h5>DSC08030<\/h5>","thumb":{"path":"thumbs\/DSC08030.webp","width":512,"height":410},"fileSize":1096190,"photodata":"<b>Original Date<\/b> <i>6\/24\/13, 7:52 PM<\/i> &middot; <b>Make<\/b> <i>SONY<\/i> &middot; <b>Camera<\/b> <i>DSC-T30<\/i> &middot; <b>Focal Length (35mm)<\/b> <i>38mm<\/i> &middot; <b>Metering Mode<\/b> <i>Multi-segment<\/i> &middot; <b>ISO Equivalent<\/b> <i>125<\/i> &middot; <b>Exposure Time<\/b> <i>1\/250s<\/i> &middot; <b>Aperture<\/b> <i>ƒ\/3.5<\/i> &middot; <b>Exposure bias<\/b> <i>0 EV<\/i> &middot; <b>Exposure Program<\/b> <i>Program normal<\/i> &middot; <b>White balance<\/b> <i>Auto white balance<\/i> &middot; <b>Flash<\/b> <i>Flash did not fire<\/i> &middot; <b>Resolution<\/b> <i>3072 x 2304<\/i>","name":"DSC08030.webp","comment":"                               ","dates":{"dateTaken":1372092772,"fileModified":1394909096},"fileDate":"2014-03-15T20:44:56.0Z","category":"image","camera":{"aperture":3.5,"exposureTime":"1\/250s","originalDate":"2013-06-24T19:52:52.0Z","cameraModel":"DSC-T30","focalLength35mm":"38mm","resolution":"3072 x 2304","cameraMake":"SONY","isoEquivalent":125,"flash":"Flash did not fire","focalLength":"6mm"}},{"path":"DSC08031.webp","image":{"path":"slides\/DSC08031.webp","width":1152,"height":1536},"imageCaption":"<h5>DSC08031<\/h5>","thumb":{"path":"thumbs\/DSC08031.webp","width":512,"height":410},"fileSize":1551788,"photodata":"<b>Original Date<\/b> <i>6\/24\/13, 7:53 PM<\/i> &middot; <b>Make<\/b> <i>SONY<\/i> &middot; <b>Camera<\/b> <i>DSC-T30<\/i> &middot; <b>Focal Length (35mm)<\/b> <i>38mm<\/i> &middot; <b>Metering Mode<\/b> <i>Multi-segment<\/i> &middot; <b>ISO Equivalent<\/b> <i>125<\/i> &middot; <b>Exposure Time<\/b> <i>1\/160s<\/i> &middot; <b>Aperture<\/b> <i>ƒ\/3.5<\/i> &middot; <b>Exposure bias<\/b> <i>0 EV<\/i> &middot; <b>Exposure Program<\/b> <i>Program normal<\/i> &middot; <b>White balance<\/b> <i>Auto white balance<\/i> &middot; <b>Flash<\/b> <i>Flash did not fire<\/i> &middot; <b>Resolution<\/b> <i>2304 x 3072<\/i>","name":"DSC08031.webp","comment":"                               ","dates":{"dateTaken":1372092785,"fileModified":1394909096},"fileDate":"2014-03-15T20:44:56.0Z","category":"image","camera":{"aperture":3.5,"exposureTime":"1\/160s","originalDate":"2013-06-24T19:53:05.0Z","cameraModel":"DSC-T30","focalLength35mm":"38mm","resolution":"2304 x 3072","cameraMake":"SONY","isoEquivalent":125,"flash":"Flash did not fire","focalLength":"6mm"}},{"path":"DSC09683.webp","image":{"path":"slides\/DSC09683.webp","width":1024,"height":768},"imageCaption":"<h5>DSC09683<\/h5>","thumb":{"path":"thumbs\/DSC09683.webp","width":512,"height":410},"fileSize":268850,"photodata":"<b>Original Date<\/b> <i>8\/24\/11, 7:02 PM<\/i> &middot; <b>Make<\/b> <i>SONY<\/i> &middot; <b>Camera<\/b> <i>DSC-T30<\/i> &middot; <b>Focal Length (35mm)<\/b> <i>38mm<\/i> &middot; <b>Metering Mode<\/b> <i>Multi-segment<\/i> &middot; <b>ISO Equivalent<\/b> <i>125<\/i> &middot; <b>Exposure Time<\/b> <i>1\/80s<\/i> &middot; <b>Aperture<\/b> <i>ƒ\/3.5<\/i> &middot; <b>Exposure bias<\/b> <i>0 EV<\/i> &middot; <b>Exposure Program<\/b> <i>Program normal<\/i> &middot; <b>White balance<\/b> <i>Auto white balance<\/i> &middot; <b>Flash<\/b> <i>Flash did not fire<\/i> &middot; <b>Resolution<\/b> <i>2048 x 1536<\/i>","name":"DSC09683.webp","comment":"                               ","dates":{"dateTaken":1314201738,"fileModified":1394909096},"fileDate":"2014-03-15T20:44:56.0Z","category":"image","camera":{"aperture":3.5,"exposureTime":"1\/80s","originalDate":"2011-08-24T19:02:18.0Z","cameraModel":"DSC-T30","focalLength35mm":"38mm","resolution":"2048 x 1536","cameraMake":"SONY","isoEquivalent":125,"flash":"Flash did not fire","focalLength":"6mm"}},{"path":"DSC09713.webp","image":{"path":"slides\/DSC09713.webp","width":1024,"height":768},"imageCaption":"<h5>DSC09713<\/h5>","thumb":{"path":"thumbs\/DSC09713.webp","width":512,"height":410},"fileSize":321764,"photodata":"<b>Original Date<\/b> <i>8\/24\/11, 7:10 PM<\/i> &middot; <b>Make<\/b> <i>SONY<\/i> &middot; <b>Camera<\/b> <i>DSC-T30<\/i> &middot; <b>Focal Length (35mm)<\/b> <i>38mm<\/i> &middot; <b>Metering Mode<\/b> <i>Multi-segment<\/i> &middot; <b>ISO Equivalent<\/b> <i>125<\/i> &middot; <b>Exposure Time<\/b> <i>1\/125s<\/i> &middot; <b>Aperture<\/b> <i>ƒ\/3.5<\/i> &middot; <b>Exposure bias<\/b> <i>0 EV<\/i> &middot; <b>Exposure Program<\/b> <i>Program normal<\/i> &middot; <b>White balance<\/b> <i>Auto white balance<\/i> &middot; <b>Flash<\/b> <i>Flash did not fire<\/i> &middot; <b>Resolution<\/b> <i>2048 x 1536<\/i>","name":"DSC09713.webp","comment":"                               ","dates":{"dateTaken":1314202207,"fileModified":1394909096},"fileDate":"2014-03-15T20:44:56.0Z","category":"image","camera":{"aperture":3.5,"exposureTime":"1\/125s","originalDate":"2011-08-24T19:10:07.0Z","cameraModel":"DSC-T30","focalLength35mm":"38mm","resolution":"2048 x 1536","cameraMake":"SONY","isoEquivalent":125,"flash":"Flash did not fire","focalLength":"6mm"}},{"path":"DSC09714.webp","image":{"path":"slides\/DSC09714.webp","width":1024,"height":768},"imageCaption":"<h5>DSC09714<\/h5>","thumb":{"path":"thumbs\/DSC09714.webp","width":512,"height":410},"fileSize":685705,"photodata":"<b>Original Date<\/b> <i>8\/24\/11, 7:10 PM<\/i> &middot; <b>Make<\/b> <i>SONY<\/i> &middot; <b>Camera<\/b> <i>DSC-T30<\/i> &middot; <b>Focal Length (35mm)<\/b> <i>38mm<\/i> &middot; <b>Metering Mode<\/b> <i>Multi-segment<\/i> &middot; <b>ISO Equivalent<\/b> <i>125<\/i> &middot; <b>Exposure Time<\/b> <i>1\/60s<\/i> &middot; <b>Aperture<\/b> <i>ƒ\/3.5<\/i> &middot; <b>Exposure bias<\/b> <i>0 EV<\/i> &middot; <b>Exposure Program<\/b> <i>Program normal<\/i> &middot; <b>White balance<\/b> <i>Auto white balance<\/i> &middot; <b>Flash<\/b> <i>Flash did not fire<\/i> &middot; <b>Resolution<\/b> <i>2048 x 1536<\/i>","name":"DSC09714.webp","comment":"                               ","dates":{"dateTaken":1314202215,"fileModified":1394909096},"fileDate":"2014-03-15T20:44:56.0Z","category":"image","camera":{"aperture":3.5,"exposureTime":"1\/60s","originalDate":"2011-08-24T19:10:15.0Z","cameraModel":"DSC-T30","focalLength35mm":"38mm","resolution":"2048 x 1536","cameraMake":"SONY","isoEquivalent":125,"flash":"Flash did not fire","focalLength":"6mm"}},{"path":"%5B000004%5D.webp","image":{"path":"slides\/%5B000004%5D.webp","width":768,"height":1024},"imageCaption":"<h5>[000004]<\/h5>","thumb":{"path":"thumbs\/%5B000004%5D.webp","width":512,"height":410},"fileSize":800796,"photodata":"<b>Original Date<\/b> <i>7\/4\/10, 5:45 AM<\/i>","name":"[000004].webp","dates":{"dateTaken":1278211552,"fileModified":1394909094},"fileDate":"2014-03-15T20:44:54.0Z","category":"image","camera":{"originalDate":"2010-07-04T05:45:52.0Z"}},{"path":"%5B000005%5D.webp","image":{"path":"slides\/%5B000005%5D.webp","width":768,"height":1024},"imageCaption":"<h5>[000005]<\/h5>","thumb":{"path":"thumbs\/%5B000005%5D.webp","width":512,"height":410},"fileSize":508444,"photodata":"<b>Original Date<\/b> <i>7\/4\/10, 5:45 AM<\/i>","name":"[000005].webp","dates":{"dateTaken":1278211552,"fileModified":1394909094},"fileDate":"2014-03-15T20:44:54.0Z","category":"image","camera":{"originalDate":"2010-07-04T05:45:52.0Z"}}],"name":"Трёхрёберник продырявленный - Tripleurospermum inodorum","dates":{"dateRange":{"0":1278211552,"1":1372092785},"fileModified":1680916802},"fileDate":"2023-01-20T18:17:50.219Z"}