{"path":"%D0%9F%D1%83%D0%B7%D1%8B%D1%80%D0%BD%D0%B8%D0%BA%20x%20%D1%81%D1%80%D0%B5%D0%B4%D0%BD%D0%B8%D0%B9%20-%20Colutea%20x%20media","deepCounters":{"total":14,"images":14,"files":14},"counters":{"total":14,"images":14,"files":14},"thumb":{"path":"thumbs\/0DSC09422.webp","width":512,"height":410},"thumbCaption":"<h3>Пузырник x средний - Colutea x media<\/h3>","album":{"description":"Herbarium.INFO Herbarium Photo Collection: Ferns, Conifers, Cycads, Flowers, Trees, Mosses, Grasses, Pests and Diseases.<br\/>\n<br\/><i><b>3111<\/b> species in <b>219<\/b> families photographed.<br\/>\n<br\/><b>35552<\/b> images total.<\/i><br\/><br\/>\nTry also other sites: <br\/>\n    <a href=\"https:\/\/herbarium.info\">Herbarium.INFO<\/a>&nbsp;\u2022&nbsp;\n    <a href=\"https:\/\/plantarium.info\">Plantarium.INFO<\/a>&nbsp;\u2022&nbsp;\n    <a href=\"https:\/\/fungarium.info\">Fungarium.INFO<\/a>&nbsp;\u2022&nbsp;\n    <a href=\"https:\/\/lichenarium.info\">Lichenarium.INFO<\/a>&nbsp;\u2022&nbsp;\n    <a href=\"https:\/\/algaerium.info\">Algaerium.INFO<\/a>","title":"Herbarium.INFO Herbs: Dicotyledones & Monocotyledones"},"objects":[{"path":"0DSC09422.webp","image":{"path":"slides\/0DSC09422.webp","width":2000,"height":1500},"imageCaption":"<h5>0DSC09422<\/h5>","thumb":{"path":"thumbs\/0DSC09422.webp","width":512,"height":410},"fileSize":2224271,"photodata":"<b>Original Date<\/b> <i>7\/15\/17, 6:37 PM<\/i> &middot; <b>Make<\/b> <i>SONY<\/i> &middot; <b>Camera<\/b> <i>DSC-HX90<\/i> &middot; <b>Lens<\/b> <i>4.1-123mm f\/3.5-6.4<\/i> &middot; <b>Focal Length (35mm)<\/b> <i>24mm<\/i> &middot; <b>Metering Mode<\/b> <i>Multi-segment<\/i> &middot; <b>ISO Equivalent<\/b> <i>800<\/i> &middot; <b>Exposure Time<\/b> <i>1\/640s<\/i> &middot; <b>Aperture<\/b> <i>ƒ\/3.5<\/i> &middot; <b>Exposure bias<\/b> <i>0 EV<\/i> &middot; <b>Exposure Program<\/b> <i>Manual control<\/i> &middot; <b>White balance<\/b> <i>Manual white balance<\/i> &middot; <b>Flash<\/b> <i>Flash did not fire<\/i> &middot; <b>Resolution<\/b> <i>4896 x 3672<\/i>","name":"0DSC09422.webp","comment":"                               ","dates":{"dateTaken":1500133043,"fileModified":1500133042},"fileDate":"2017-07-15T18:37:22.0Z","category":"image","camera":{"aperture":3.5,"exposureTime":"1\/640s","originalDate":"2017-07-15T18:37:23.0Z","cameraModel":"DSC-HX90","focalLength35mm":"24mm","resolution":"4896 x 3672","cameraMake":"SONY","isoEquivalent":800,"flash":"Flash did not fire","focalLength":"4mm"}},{"image":{"path":"slides\/DSC04209.webp","width":2000,"height":1500},"thumb":{"path":"thumbs\/DSC04209.webp","width":512,"height":410},"photodata":"<b>Original Date<\/b> <i>6\/26\/21, 2:45 PM<\/i> &middot; <b>Make<\/b> <i>SONY<\/i> &middot; <b>Camera<\/b> <i>DSC-HX90V<\/i> &middot; <b>Lens<\/b> <i>4.1-123mm f\/3.5-6.4<\/i> &middot; <b>Focal Length (35mm)<\/b> <i>24mm<\/i> &middot; <b>Metering Mode<\/b> <i>Spot<\/i> &middot; <b>ISO Equivalent<\/b> <i>80<\/i> &middot; <b>Exposure Time<\/b> <i>1\/100s<\/i> &middot; <b>Aperture<\/b> <i>ƒ\/3.5<\/i> &middot; <b>Exposure bias<\/b> <i>0 EV<\/i> &middot; <b>Exposure Program<\/b> <i>Manual control<\/i> &middot; <b>White balance<\/b> <i>Manual white balance<\/i> &middot; <b>Flash<\/b> <i>Flash did not fire<\/i> &middot; <b>Resolution<\/b> <i>4896 x 3672<\/i>","dates":{"dateTaken":1624707919,"fileModified":1624707918},"fileDate":"2021-06-26T14:45:18.0Z","path":"DSC04209.webp","imageCaption":"<h5>DSC04209<\/h5>","fileSize":8307003,"name":"DSC04209.webp","comment":"                               ","location":"59.466836,24.876650","category":"image","camera":{"aperture":3.5,"exposureTime":"1\/100s","originalDate":"2021-06-26T14:45:19.0Z","cameraModel":"DSC-HX90V","location":{"altitude":"8 metres","latitude":"59° 28' 0.61\"","lat":59.466835,"long":24.87665,"longitude":"24° 52' 35.94\""},"focalLength35mm":"24mm","resolution":"4896 x 3672","cameraMake":"SONY","isoEquivalent":80,"flash":"Flash did not fire","focalLength":"4mm"}},{"image":{"path":"slides\/DSC04210.webp","width":2000,"height":1500},"thumb":{"path":"thumbs\/DSC04210.webp","width":512,"height":410},"photodata":"<b>Original Date<\/b> <i>6\/26\/21, 2:45 PM<\/i> &middot; <b>Make<\/b> <i>SONY<\/i> &middot; <b>Camera<\/b> <i>DSC-HX90V<\/i> &middot; <b>Lens<\/b> <i>4.1-123mm f\/3.5-6.4<\/i> &middot; <b>Focal Length (35mm)<\/b> <i>24mm<\/i> &middot; <b>Metering Mode<\/b> <i>Spot<\/i> &middot; <b>ISO Equivalent<\/b> <i>80<\/i> &middot; <b>Exposure Time<\/b> <i>1\/100s<\/i> &middot; <b>Aperture<\/b> <i>ƒ\/3.5<\/i> &middot; <b>Exposure bias<\/b> <i>0 EV<\/i> &middot; <b>Exposure Program<\/b> <i>Manual control<\/i> &middot; <b>White balance<\/b> <i>Manual white balance<\/i> &middot; <b>Flash<\/b> <i>Flash did not fire<\/i> &middot; <b>Resolution<\/b> <i>4896 x 3672<\/i>","dates":{"dateTaken":1624707924,"fileModified":1624707924},"fileDate":"2021-06-26T14:45:24.0Z","path":"DSC04210.webp","imageCaption":"<h5>DSC04210<\/h5>","fileSize":6152364,"name":"DSC04210.webp","comment":"                               ","location":"59.466835,24.876656","category":"image","camera":{"aperture":3.5,"exposureTime":"1\/100s","originalDate":"2021-06-26T14:45:24.0Z","cameraModel":"DSC-HX90V","location":{"altitude":"8.2 metres","latitude":"59° 28' 0.61\"","lat":59.466835,"long":24.876656,"longitude":"24° 52' 35.96\""},"focalLength35mm":"24mm","resolution":"4896 x 3672","cameraMake":"SONY","isoEquivalent":80,"flash":"Flash did not fire","focalLength":"4mm"}},{"image":{"path":"slides\/DSC04211.webp","width":2000,"height":1500},"thumb":{"path":"thumbs\/DSC04211.webp","width":512,"height":410},"photodata":"<b>Original Date<\/b> <i>6\/26\/21, 2:45 PM<\/i> &middot; <b>Make<\/b> <i>SONY<\/i> &middot; <b>Camera<\/b> <i>DSC-HX90V<\/i> &middot; <b>Lens<\/b> <i>4.1-123mm f\/3.5-6.4<\/i> &middot; <b>Focal Length (35mm)<\/b> <i>24mm<\/i> &middot; <b>Metering Mode<\/b> <i>Spot<\/i> &middot; <b>ISO Equivalent<\/b> <i>80<\/i> &middot; <b>Exposure Time<\/b> <i>1\/100s<\/i> &middot; <b>Aperture<\/b> <i>ƒ\/3.5<\/i> &middot; <b>Exposure bias<\/b> <i>0 EV<\/i> &middot; <b>Exposure Program<\/b> <i>Manual control<\/i> &middot; <b>White balance<\/b> <i>Manual white balance<\/i> &middot; <b>Flash<\/b> <i>Flash did not fire<\/i> &middot; <b>Resolution<\/b> <i>4896 x 3672<\/i>","dates":{"dateTaken":1624707931,"fileModified":1624707930},"fileDate":"2021-06-26T14:45:30.0Z","path":"DSC04211.webp","imageCaption":"<h5>DSC04211<\/h5>","fileSize":9240776,"name":"DSC04211.webp","comment":"                               ","location":"59.466836,24.876635","category":"image","camera":{"aperture":3.5,"exposureTime":"1\/100s","originalDate":"2021-06-26T14:45:31.0Z","cameraModel":"DSC-HX90V","location":{"altitude":"7.9 metres","latitude":"59° 28' 0.61\"","lat":59.466835,"long":24.876635,"longitude":"24° 52' 35.89\""},"focalLength35mm":"24mm","resolution":"4896 x 3672","cameraMake":"SONY","isoEquivalent":80,"flash":"Flash did not fire","focalLength":"4mm"}},{"image":{"path":"slides\/DSC04212.webp","width":2000,"height":1500},"thumb":{"path":"thumbs\/DSC04212.webp","width":512,"height":410},"photodata":"<b>Original Date<\/b> <i>6\/26\/21, 2:45 PM<\/i> &middot; <b>Make<\/b> <i>SONY<\/i> &middot; <b>Camera<\/b> <i>DSC-HX90V<\/i> &middot; <b>Lens<\/b> <i>4.1-123mm f\/3.5-6.4<\/i> &middot; <b>Focal Length (35mm)<\/b> <i>24mm<\/i> &middot; <b>Metering Mode<\/b> <i>Spot<\/i> &middot; <b>ISO Equivalent<\/b> <i>80<\/i> &middot; <b>Exposure Time<\/b> <i>1\/125s<\/i> &middot; <b>Aperture<\/b> <i>ƒ\/3.5<\/i> &middot; <b>Exposure bias<\/b> <i>0 EV<\/i> &middot; <b>Exposure Program<\/b> <i>Manual control<\/i> &middot; <b>White balance<\/b> <i>Manual white balance<\/i> &middot; <b>Flash<\/b> <i>Flash did not fire<\/i> &middot; <b>Resolution<\/b> <i>4896 x 3672<\/i>","dates":{"dateTaken":1624707941,"fileModified":1624707940},"fileDate":"2021-06-26T14:45:40.0Z","path":"DSC04212.webp","imageCaption":"<h5>DSC04212<\/h5>","fileSize":8873242,"name":"DSC04212.webp","comment":"                               ","location":"59.466860,24.876560","category":"image","camera":{"aperture":3.5,"exposureTime":"1\/125s","originalDate":"2021-06-26T14:45:41.0Z","cameraModel":"DSC-HX90V","location":{"altitude":"7.6 metres","latitude":"59° 28' 0.7\"","lat":59.46686,"long":24.87656,"longitude":"24° 52' 35.62\""},"focalLength35mm":"24mm","resolution":"4896 x 3672","cameraMake":"SONY","isoEquivalent":80,"flash":"Flash did not fire","focalLength":"4mm"}},{"image":{"path":"slides\/DSC04213.webp","width":2000,"height":1500},"thumb":{"path":"thumbs\/DSC04213.webp","width":512,"height":410},"photodata":"<b>Original Date<\/b> <i>6\/26\/21, 2:45 PM<\/i> &middot; <b>Make<\/b> <i>SONY<\/i> &middot; <b>Camera<\/b> <i>DSC-HX90V<\/i> &middot; <b>Lens<\/b> <i>4.1-123mm f\/3.5-6.4<\/i> &middot; <b>Focal Length (35mm)<\/b> <i>24mm<\/i> &middot; <b>Metering Mode<\/b> <i>Spot<\/i> &middot; <b>ISO Equivalent<\/b> <i>80<\/i> &middot; <b>Exposure Time<\/b> <i>1\/100s<\/i> &middot; <b>Aperture<\/b> <i>ƒ\/3.5<\/i> &middot; <b>Exposure bias<\/b> <i>0 EV<\/i> &middot; <b>Exposure Program<\/b> <i>Manual control<\/i> &middot; <b>White balance<\/b> <i>Manual white balance<\/i> &middot; <b>Flash<\/b> <i>Flash did not fire<\/i> &middot; <b>Resolution<\/b> <i>4896 x 3672<\/i>","dates":{"dateTaken":1624707947,"fileModified":1624707946},"fileDate":"2021-06-26T14:45:46.0Z","path":"DSC04213.webp","imageCaption":"<h5>DSC04213<\/h5>","fileSize":6421435,"name":"DSC04213.webp","comment":"                               ","location":"59.466883,24.876500","category":"image","camera":{"aperture":3.5,"exposureTime":"1\/100s","originalDate":"2021-06-26T14:45:47.0Z","cameraModel":"DSC-HX90V","location":{"altitude":"7.8 metres","latitude":"59° 28' 0.78\"","lat":59.466885,"long":24.8765,"longitude":"24° 52' 35.4\""},"focalLength35mm":"24mm","resolution":"4896 x 3672","cameraMake":"SONY","isoEquivalent":80,"flash":"Flash did not fire","focalLength":"4mm"}},{"image":{"path":"slides\/DSC04214.webp","width":2000,"height":1500},"thumb":{"path":"thumbs\/DSC04214.webp","width":512,"height":410},"photodata":"<b>Original Date<\/b> <i>6\/26\/21, 2:45 PM<\/i> &middot; <b>Make<\/b> <i>SONY<\/i> &middot; <b>Camera<\/b> <i>DSC-HX90V<\/i> &middot; <b>Lens<\/b> <i>4.1-123mm f\/3.5-6.4<\/i> &middot; <b>Focal Length (35mm)<\/b> <i>24mm<\/i> &middot; <b>Metering Mode<\/b> <i>Spot<\/i> &middot; <b>ISO Equivalent<\/b> <i>80<\/i> &middot; <b>Exposure Time<\/b> <i>1\/80s<\/i> &middot; <b>Aperture<\/b> <i>ƒ\/3.5<\/i> &middot; <b>Exposure bias<\/b> <i>0 EV<\/i> &middot; <b>Exposure Program<\/b> <i>Manual control<\/i> &middot; <b>White balance<\/b> <i>Manual white balance<\/i> &middot; <b>Flash<\/b> <i>Flash did not fire<\/i> &middot; <b>Resolution<\/b> <i>4896 x 3672<\/i>","dates":{"dateTaken":1624707959,"fileModified":1624707958},"fileDate":"2021-06-26T14:45:58.0Z","path":"DSC04214.webp","imageCaption":"<h5>DSC04214<\/h5>","fileSize":8446195,"name":"DSC04214.webp","comment":"                               ","location":"59.466875,24.876483","category":"image","camera":{"aperture":3.5,"exposureTime":"1\/80s","originalDate":"2021-06-26T14:45:59.0Z","cameraModel":"DSC-HX90V","location":{"altitude":"7.1 metres","latitude":"59° 28' 0.75\"","lat":59.466873,"long":24.876484,"longitude":"24° 52' 35.34\""},"focalLength35mm":"24mm","resolution":"4896 x 3672","cameraMake":"SONY","isoEquivalent":80,"flash":"Flash did not fire","focalLength":"4mm"}},{"image":{"path":"slides\/DSC04215.webp","width":2000,"height":1500},"thumb":{"path":"thumbs\/DSC04215.webp","width":512,"height":410},"photodata":"<b>Original Date<\/b> <i>6\/26\/21, 2:46 PM<\/i> &middot; <b>Make<\/b> <i>SONY<\/i> &middot; <b>Camera<\/b> <i>DSC-HX90V<\/i> &middot; <b>Lens<\/b> <i>4.1-123mm f\/3.5-6.4<\/i> &middot; <b>Focal Length (35mm)<\/b> <i>24mm<\/i> &middot; <b>Metering Mode<\/b> <i>Spot<\/i> &middot; <b>ISO Equivalent<\/b> <i>80<\/i> &middot; <b>Exposure Time<\/b> <i>1\/80s<\/i> &middot; <b>Aperture<\/b> <i>ƒ\/3.5<\/i> &middot; <b>Exposure bias<\/b> <i>0 EV<\/i> &middot; <b>Exposure Program<\/b> <i>Manual control<\/i> &middot; <b>White balance<\/b> <i>Manual white balance<\/i> &middot; <b>Flash<\/b> <i>Flash did not fire<\/i> &middot; <b>Resolution<\/b> <i>4896 x 3672<\/i>","dates":{"dateTaken":1624707968,"fileModified":1624707968},"fileDate":"2021-06-26T14:46:08.0Z","path":"DSC04215.webp","imageCaption":"<h5>DSC04215<\/h5>","fileSize":6945712,"name":"DSC04215.webp","comment":"                               ","location":"59.466841,24.876560","category":"image","camera":{"aperture":3.5,"exposureTime":"1\/80s","originalDate":"2021-06-26T14:46:08.0Z","cameraModel":"DSC-HX90V","location":{"altitude":"6.1 metres","latitude":"59° 28' 0.63\"","lat":59.466843,"long":24.87656,"longitude":"24° 52' 35.62\""},"focalLength35mm":"24mm","resolution":"4896 x 3672","cameraMake":"SONY","isoEquivalent":80,"flash":"Flash did not fire","focalLength":"4mm"}},{"path":"DSC09423.webp","image":{"path":"slides\/DSC09423.webp","width":1500,"height":2000},"imageCaption":"<h5>DSC09423<\/h5>","thumb":{"path":"thumbs\/DSC09423.webp","width":512,"height":410},"fileSize":2127293,"photodata":"<b>Original Date<\/b> <i>7\/15\/17, 6:37 PM<\/i> &middot; <b>Make<\/b> <i>SONY<\/i> &middot; <b>Camera<\/b> <i>DSC-HX90<\/i> &middot; <b>Lens<\/b> <i>4.1-123mm f\/3.5-6.4<\/i> &middot; <b>Focal Length (35mm)<\/b> <i>24mm<\/i> &middot; <b>Metering Mode<\/b> <i>Multi-segment<\/i> &middot; <b>ISO Equivalent<\/b> <i>800<\/i> &middot; <b>Exposure Time<\/b> <i>1\/640s<\/i> &middot; <b>Aperture<\/b> <i>ƒ\/3.5<\/i> &middot; <b>Exposure bias<\/b> <i>0 EV<\/i> &middot; <b>Exposure Program<\/b> <i>Manual control<\/i> &middot; <b>White balance<\/b> <i>Manual white balance<\/i> &middot; <b>Flash<\/b> <i>Flash did not fire<\/i> &middot; <b>Resolution<\/b> <i>3672 x 4896<\/i>","name":"DSC09423.webp","comment":"                               ","dates":{"dateTaken":1500133050,"fileModified":1500133050},"fileDate":"2017-07-15T18:37:30.0Z","category":"image","camera":{"aperture":3.5,"exposureTime":"1\/640s","originalDate":"2017-07-15T18:37:30.0Z","cameraModel":"DSC-HX90","focalLength35mm":"24mm","resolution":"3672 x 4896","cameraMake":"SONY","isoEquivalent":800,"flash":"Flash did not fire","focalLength":"4mm"}},{"path":"DSC09424.webp","image":{"path":"slides\/DSC09424.webp","width":2000,"height":1500},"imageCaption":"<h5>DSC09424<\/h5>","thumb":{"path":"thumbs\/DSC09424.webp","width":512,"height":410},"fileSize":2299193,"photodata":"<b>Original Date<\/b> <i>7\/15\/17, 6:37 PM<\/i> &middot; <b>Make<\/b> <i>SONY<\/i> &middot; <b>Camera<\/b> <i>DSC-HX90<\/i> &middot; <b>Lens<\/b> <i>4.1-123mm f\/3.5-6.4<\/i> &middot; <b>Focal Length (35mm)<\/b> <i>24mm<\/i> &middot; <b>Metering Mode<\/b> <i>Multi-segment<\/i> &middot; <b>ISO Equivalent<\/b> <i>800<\/i> &middot; <b>Exposure Time<\/b> <i>1\/640s<\/i> &middot; <b>Aperture<\/b> <i>ƒ\/3.5<\/i> &middot; <b>Exposure bias<\/b> <i>0 EV<\/i> &middot; <b>Exposure Program<\/b> <i>Manual control<\/i> &middot; <b>White balance<\/b> <i>Manual white balance<\/i> &middot; <b>Flash<\/b> <i>Flash did not fire<\/i> &middot; <b>Resolution<\/b> <i>4896 x 3672<\/i>","name":"DSC09424.webp","comment":"                               ","dates":{"dateTaken":1500133057,"fileModified":1500133056},"fileDate":"2017-07-15T18:37:36.0Z","category":"image","camera":{"aperture":3.5,"exposureTime":"1\/640s","originalDate":"2017-07-15T18:37:37.0Z","cameraModel":"DSC-HX90","focalLength35mm":"24mm","resolution":"4896 x 3672","cameraMake":"SONY","isoEquivalent":800,"flash":"Flash did not fire","focalLength":"4mm"}},{"path":"DSC09425.webp","image":{"path":"slides\/DSC09425.webp","width":2000,"height":1500},"imageCaption":"<h5>DSC09425<\/h5>","thumb":{"path":"thumbs\/DSC09425.webp","width":512,"height":410},"fileSize":2961704,"photodata":"<b>Original Date<\/b> <i>7\/15\/17, 6:37 PM<\/i> &middot; <b>Make<\/b> <i>SONY<\/i> &middot; <b>Camera<\/b> <i>DSC-HX90<\/i> &middot; <b>Lens<\/b> <i>4.1-123mm f\/3.5-6.4<\/i> &middot; <b>Focal Length (35mm)<\/b> <i>24mm<\/i> &middot; <b>Metering Mode<\/b> <i>Multi-segment<\/i> &middot; <b>ISO Equivalent<\/b> <i>800<\/i> &middot; <b>Exposure Time<\/b> <i>1\/640s<\/i> &middot; <b>Aperture<\/b> <i>ƒ\/3.5<\/i> &middot; <b>Exposure bias<\/b> <i>0 EV<\/i> &middot; <b>Exposure Program<\/b> <i>Manual control<\/i> &middot; <b>White balance<\/b> <i>Manual white balance<\/i> &middot; <b>Flash<\/b> <i>Flash did not fire<\/i> &middot; <b>Resolution<\/b> <i>4896 x 3672<\/i>","name":"DSC09425.webp","comment":"                               ","dates":{"dateTaken":1500133063,"fileModified":1500133064},"fileDate":"2017-07-15T18:37:44.0Z","category":"image","camera":{"aperture":3.5,"exposureTime":"1\/640s","originalDate":"2017-07-15T18:37:43.0Z","cameraModel":"DSC-HX90","focalLength35mm":"24mm","resolution":"4896 x 3672","cameraMake":"SONY","isoEquivalent":800,"flash":"Flash did not fire","focalLength":"4mm"}},{"path":"DSC09426.webp","image":{"path":"slides\/DSC09426.webp","width":1500,"height":2000},"imageCaption":"<h5>DSC09426<\/h5>","thumb":{"path":"thumbs\/DSC09426.webp","width":512,"height":410},"fileSize":2278709,"photodata":"<b>Original Date<\/b> <i>7\/15\/17, 6:37 PM<\/i> &middot; <b>Make<\/b> <i>SONY<\/i> &middot; <b>Camera<\/b> <i>DSC-HX90<\/i> &middot; <b>Lens<\/b> <i>4.1-123mm f\/3.5-6.4<\/i> &middot; <b>Focal Length (35mm)<\/b> <i>24mm<\/i> &middot; <b>Metering Mode<\/b> <i>Multi-segment<\/i> &middot; <b>ISO Equivalent<\/b> <i>800<\/i> &middot; <b>Exposure Time<\/b> <i>1\/640s<\/i> &middot; <b>Aperture<\/b> <i>ƒ\/3.5<\/i> &middot; <b>Exposure bias<\/b> <i>0 EV<\/i> &middot; <b>Exposure Program<\/b> <i>Manual control<\/i> &middot; <b>White balance<\/b> <i>Manual white balance<\/i> &middot; <b>Flash<\/b> <i>Flash did not fire<\/i> &middot; <b>Resolution<\/b> <i>3672 x 4896<\/i>","name":"DSC09426.webp","comment":"                               ","dates":{"dateTaken":1500133077,"fileModified":1500133078},"fileDate":"2017-07-15T18:37:58.0Z","category":"image","camera":{"aperture":3.5,"exposureTime":"1\/640s","originalDate":"2017-07-15T18:37:57.0Z","cameraModel":"DSC-HX90","focalLength35mm":"24mm","resolution":"3672 x 4896","cameraMake":"SONY","isoEquivalent":800,"flash":"Flash did not fire","focalLength":"4mm"}},{"path":"DSC09427.webp","image":{"path":"slides\/DSC09427.webp","width":2000,"height":1500},"imageCaption":"<h5>DSC09427<\/h5>","thumb":{"path":"thumbs\/DSC09427.webp","width":512,"height":410},"fileSize":2567001,"photodata":"<b>Original Date<\/b> <i>7\/15\/17, 6:38 PM<\/i> &middot; <b>Make<\/b> <i>SONY<\/i> &middot; <b>Camera<\/b> <i>DSC-HX90<\/i> &middot; <b>Lens<\/b> <i>4.1-123mm f\/3.5-6.4<\/i> &middot; <b>Focal Length (35mm)<\/b> <i>24mm<\/i> &middot; <b>Metering Mode<\/b> <i>Multi-segment<\/i> &middot; <b>ISO Equivalent<\/b> <i>800<\/i> &middot; <b>Exposure Time<\/b> <i>1\/640s<\/i> &middot; <b>Aperture<\/b> <i>ƒ\/3.5<\/i> &middot; <b>Exposure bias<\/b> <i>0 EV<\/i> &middot; <b>Exposure Program<\/b> <i>Manual control<\/i> &middot; <b>White balance<\/b> <i>Manual white balance<\/i> &middot; <b>Flash<\/b> <i>Flash did not fire<\/i> &middot; <b>Resolution<\/b> <i>4896 x 3672<\/i>","name":"DSC09427.webp","comment":"                               ","dates":{"dateTaken":1500133092,"fileModified":1500133094},"fileDate":"2017-07-15T18:38:14.0Z","category":"image","camera":{"aperture":3.5,"exposureTime":"1\/640s","originalDate":"2017-07-15T18:38:12.0Z","cameraModel":"DSC-HX90","focalLength35mm":"24mm","resolution":"4896 x 3672","cameraMake":"SONY","isoEquivalent":800,"flash":"Flash did not fire","focalLength":"4mm"}},{"path":"DSC09428.webp","image":{"path":"slides\/DSC09428.webp","width":2000,"height":1500},"imageCaption":"<h5>DSC09428<\/h5>","thumb":{"path":"thumbs\/DSC09428.webp","width":512,"height":410},"fileSize":2106856,"photodata":"<b>Original Date<\/b> <i>7\/15\/17, 6:38 PM<\/i> &middot; <b>Make<\/b> <i>SONY<\/i> &middot; <b>Camera<\/b> <i>DSC-HX90<\/i> &middot; <b>Lens<\/b> <i>4.1-123mm f\/3.5-6.4<\/i> &middot; <b>Focal Length (35mm)<\/b> <i>34mm<\/i> &middot; <b>Metering Mode<\/b> <i>Multi-segment<\/i> &middot; <b>ISO Equivalent<\/b> <i>800<\/i> &middot; <b>Exposure Time<\/b> <i>1\/640s<\/i> &middot; <b>Aperture<\/b> <i>ƒ\/4<\/i> &middot; <b>Exposure bias<\/b> <i>0 EV<\/i> &middot; <b>Exposure Program<\/b> <i>Manual control<\/i> &middot; <b>White balance<\/b> <i>Manual white balance<\/i> &middot; <b>Flash<\/b> <i>Flash did not fire<\/i> &middot; <b>Resolution<\/b> <i>4896 x 3672<\/i>","name":"DSC09428.webp","comment":"                               ","dates":{"dateTaken":1500133104,"fileModified":1500133106},"fileDate":"2017-07-15T18:38:26.0Z","category":"image","camera":{"aperture":4.0,"exposureTime":"1\/640s","originalDate":"2017-07-15T18:38:24.0Z","cameraModel":"DSC-HX90","focalLength35mm":"34mm","resolution":"4896 x 3672","cameraMake":"SONY","isoEquivalent":800,"flash":"Flash did not fire","focalLength":"6mm"}}],"name":"Пузырник x средний - Colutea x media","dates":{"dateRange":{"0":1500133043,"1":1624707968},"fileModified":1680916804},"fileDate":"2023-01-20T18:13:52.262Z"}